{
  "root_group": {
    "groups": [],
    "checks": [
        {
          "name": "status is 200",
          "path": "::status is 200",
          "id": "6210a8cd14cd70477eba5c5e4cb3fb5f",
          "passes": 2251,
          "fails": 0
        },
        {
          "fails": 0,
          "name": "no graphql errors",
          "path": "::no graphql errors",
          "id": "7c29382b2a87caa2e50f0d89170b649f",
          "passes": 2251
        }
      ],
    "name": "",
    "path": "",
    "id": "d41d8cd98f00b204e9800998ecf8427e"
  },
  "options": {
    "summaryTrendStats": [
      "avg",
      "min",
      "med",
      "max",
      "p(50)",
      "p(95)",
      "p(99)"
    ],
    "summaryTimeUnit": "",
    "noColor": false
  },
  "state": {
    "isStdOutTTY": false,
    "isStdErrTTY": false,
    "testRunDurationMs": 90015.390892
  },
  "metrics": {
    "http_req_tls_handshaking": {
      "type": "trend",
      "contains": "time",
      "values": {
        "p(95)": 0,
        "p(99)": 0,
        "avg": 0,
        "min": 0,
        "med": 0,
        "max": 0,
        "p(50)": 0
      }
    },
    "req_latency": {
      "type": "trend",
      "contains": "default",
      "values": {
        "avg": 15.883460899600205,
        "min": 10.115005,
        "med": 15.835943,
        "max": 93.273622,
        "p(50)": 15.835943,
        "p(95)": 19.2568475,
        "p(99)": 22.681994
      }
    },
    "http_reqs": {
      "contains": "default",
      "values": {
        "count": 2251,
        "rate": 25.006834694532827
      },
      "type": "counter"
    },
    "round_trip_count": {
      "type": "trend",
      "contains": "default",
      "values": {
        "p(95)": 1,
        "p(99)": 1,
        "avg": 1,
        "min": 1,
        "med": 1,
        "max": 1,
        "p(50)": 1
      }
    },
    "vus_max": {
      "type": "gauge",
      "contains": "default",
      "values": {
        "value": 50,
        "min": 50,
        "max": 50
      }
    },
    "http_req_duration": {
      "type": "trend",
      "contains": "time",
      "values": {
        "min": 10.115005,
        "med": 15.835943,
        "max": 93.273622,
        "p(50)": 15.835943,
        "p(95)": 19.2568475,
        "p(99)": 22.681994,
        "avg": 15.883460899600205
      }
    },
    "http_req_blocked": {
      "type": "trend",
      "contains": "time",
      "values": {
        "p(50)": 0.00748,
        "p(95)": 0.016715,
        "p(99)": 5.3888245,
        "avg": 0.1277016734784535,
        "min": 0.00453,
        "med": 0.00748,
        "max": 8.979091
      }
    },
    "payload_bytes": {
      "contains": "default",
      "values": {
        "avg": 2960.4891159484673,
        "min": 634,
        "med": 3474,
        "max": 29374,
        "p(50)": 3474,
        "p(95)": 5158,
        "p(99)": 5321
      },
      "type": "trend"
    },
    "data_sent": {
      "type": "counter",
      "contains": "data",
      "values": {
        "count": 597795,
        "rate": 6641.030984548313
      }
    },
    "vus": {
      "type": "gauge",
      "contains": "default",
      "values": {
        "value": 0,
        "min": 0,
        "max": 1
      }
    },
    "http_req_connecting": {
      "type": "trend",
      "contains": "time",
      "values": {
        "p(95)": 0,
        "p(99)": 5.29513,
        "avg": 0.11707417503331848,
        "min": 0,
        "med": 0,
        "max": 8.899771,
        "p(50)": 0
      }
    },
    "iterations": {
      "type": "counter",
      "contains": "default",
      "values": {
        "count": 2251,
        "rate": 25.006834694532827
      }
    },
    "http_req_waiting": {
      "type": "trend",
      "contains": "time",
      "values": {
        "p(50)": 15.693164,
        "p(95)": 19.121854,
        "p(99)": 22.5098855,
        "avg": 15.735322621057314,
        "min": 9.987785,
        "med": 15.693164,
        "max": 86.953127
      }
    },
    "checks": {
      "type": "rate",
      "contains": "default",
      "values": {
        "fails": 0,
        "rate": 1,
        "passes": 4502
      }
    },
    "http_req_duration{expected_response:true}": {
      "type": "trend",
      "contains": "time",
      "values": {
        "avg": 15.883460899600205,
        "min": 10.115005,
        "med": 15.835943,
        "max": 93.273622,
        "p(50)": 15.835943,
        "p(95)": 19.2568475,
        "p(99)": 22.681994
      }
    },
    "iteration_duration": {
      "type": "trend",
      "contains": "time",
      "values": {
        "p(95)": 21.615850000000002,
        "p(99)": 26.493788000000002,
        "avg": 17.441376517547788,
        "min": 10.869961,
        "med": 17.432074,
        "max": 102.141963,
        "p(50)": 17.432074
      }
    },
    "http_req_receiving": {
      "type": "trend",
      "contains": "time",
      "values": {
        "p(99)": 0.218579,
        "avg": 0.11290444380275451,
        "min": 0.04644,
        "med": 0.100019,
        "max": 7.076691,
        "p(50)": 0.100019,
        "p(95)": 0.154359
      }
    },
    "http_req_failed": {
      "values": {
        "rate": 0,
        "passes": 0,
        "fails": 2251
      },
      "type": "rate",
      "contains": "default"
    },
    "http_req_sending": {
      "contains": "time",
      "values": {
        "med": 0.028939,
        "max": 0.215899,
        "p(50)": 0.028939,
        "p(95)": 0.07896449999999999,
        "p(99)": 0.1243395,
        "avg": 0.035233834740115454,
        "min": 0.01364
      },
      "type": "trend"
    },
    "data_received": {
      "type": "counter",
      "contains": "data",
      "values": {
        "count": 7253183,
        "rate": 80577.142732206
      }
    }
  }
}