{
  "root_group": {
    "checks": [
      {
        "name": "status is 200",
        "path": "::status is 200",
        "id": "6210a8cd14cd70477eba5c5e4cb3fb5f",
        "passes": 6661,
        "fails": 0
      },
      {
        "name": "no graphql errors",
        "path": "::no graphql errors",
        "id": "7c29382b2a87caa2e50f0d89170b649f",
        "passes": 6661,
        "fails": 0
      }
    ],
    "name": "",
    "path": "",
    "id": "d41d8cd98f00b204e9800998ecf8427e",
    "groups": []
  },
  "options": {
    "noColor": false,
    "summaryTrendStats": [
      "avg",
      "min",
      "med",
      "max",
      "p(50)",
      "p(95)",
      "p(99)"
    ],
    "summaryTimeUnit": ""
  },
  "state": {
    "isStdOutTTY": false,
    "isStdErrTTY": false,
    "testRunDurationMs": 90015.480786
  },
  "metrics": {
    "data_received": {
      "type": "counter",
      "contains": "data",
      "values": {
        "count": 4027130,
        "rate": 44738.19352888836
      }
    },
    "http_req_connecting": {
      "values": {
        "p(50)": 0,
        "p(95)": 0,
        "p(99)": 5.404342399999993,
        "avg": 0.11983705359555627,
        "min": 0,
        "med": 0,
        "max": 16.805658
      },
      "type": "trend",
      "contains": "time"
    },
    "http_req_blocked": {
      "type": "trend",
      "contains": "time",
      "values": {
        "p(99)": 5.505052799999999,
        "avg": 0.1310499034679472,
        "min": 0.00446,
        "med": 0.00802,
        "max": 16.875278,
        "p(50)": 0.00802,
        "p(95)": 0.01578
      }
    },
    "http_req_sending": {
      "type": "trend",
      "contains": "time",
      "values": {
        "min": 0.01305,
        "med": 0.02788,
        "max": 0.222918,
        "p(50)": 0.02788,
        "p(95)": 0.059279,
        "p(99)": 0.11421759999999957,
        "avg": 0.03287234649452045
      }
    },
    "http_req_duration{expected_response:true}": {
      "type": "trend",
      "contains": "time",
      "values": {
        "p(50)": 13.58857,
        "p(95)": 28.241973,
        "p(99)": 74.96015739999993,
        "avg": 16.065035348596272,
        "min": 9.22572,
        "med": 13.58857,
        "max": 111.74152
      }
    },
    "vus": {
      "type": "gauge",
      "contains": "default",
      "values": {
        "value": 1,
        "min": 1,
        "max": 6
      }
    },
    "data_sent": {
      "type": "counter",
      "contains": "data",
      "values": {
        "rate": 19683.325407240023,
        "count": 1771804
      }
    },
    "http_req_waiting": {
      "type": "trend",
      "contains": "time",
      "values": {
        "p(99)": 73.80323739999996,
        "avg": 15.835992114397214,
        "min": 9.107341,
        "med": 13.437962,
        "max": 110.023031,
        "p(50)": 13.437962,
        "p(95)": 27.52698
      }
    },
    "round_trip_count": {
      "type": "trend",
      "contains": "default",
      "values": {
        "p(99)": 1,
        "avg": 1,
        "min": 1,
        "med": 1,
        "max": 1,
        "p(50)": 1,
        "p(95)": 1
      }
    },
    "http_req_tls_handshaking": {
      "type": "trend",
      "contains": "time",
      "values": {
        "p(95)": 0,
        "p(99)": 0,
        "avg": 0,
        "min": 0,
        "med": 0,
        "max": 0,
        "p(50)": 0
      }
    },
    "http_req_failed": {
      "type": "rate",
      "contains": "default",
      "values": {
        "fails": 6661,
        "rate": 0,
        "passes": 0
      }
    },
    "http_reqs": {
      "type": "counter",
      "contains": "default",
      "values": {
        "count": 6661,
        "rate": 73.99838274302677
      }
    },
    "iteration_duration": {
      "type": "trend",
      "contains": "time",
      "values": {
        "med": 14.161658,
        "max": 112.182837,
        "p(50)": 14.161658,
        "p(95)": 28.809551,
        "p(99)": 75.5768588,
        "avg": 16.75028338988142,
        "min": 9.869256
      }
    },
    "vus_max": {
      "type": "gauge",
      "contains": "default",
      "values": {
        "value": 148,
        "min": 148,
        "max": 148
      }
    },
    "req_latency": {
      "type": "trend",
      "contains": "default",
      "values": {
        "min": 9.22572,
        "med": 13.58857,
        "max": 111.74152,
        "p(50)": 13.58857,
        "p(95)": 28.241973,
        "p(99)": 74.96015739999993,
        "avg": 16.065035348596272
      }
    },
    "iterations": {
      "contains": "default",
      "values": {
        "count": 6661,
        "rate": 73.99838274302677
      },
      "type": "counter"
    },
    "payload_bytes": {
      "values": {
        "p(50)": 348,
        "p(95)": 447,
        "p(99)": 450,
        "avg": 343.5833958865035,
        "min": 147,
        "med": 348,
        "max": 547
      },
      "type": "trend",
      "contains": "default"
    },
    "checks": {
      "type": "rate",
      "contains": "default",
      "values": {
        "rate": 1,
        "passes": 13322,
        "fails": 0
      }
    },
    "http_req_receiving": {
      "contains": "time",
      "values": {
        "min": 0.03201,
        "med": 0.09318,
        "max": 15.068411,
        "p(50)": 0.09318,
        "p(95)": 0.377578,
        "p(99)": 1.4912919999999916,
        "avg": 0.19617088770454852
      },
      "type": "trend"
    },
    "http_req_duration": {
      "values": {
        "med": 13.58857,
        "max": 111.74152,
        "p(50)": 13.58857,
        "p(95)": 28.241973,
        "p(99)": 74.96015739999993,
        "avg": 16.065035348596272,
        "min": 9.22572
      },
      "type": "trend",
      "contains": "time"
    }
  }
}