{
  "root_group": {
    "id": "d41d8cd98f00b204e9800998ecf8427e",
    "groups": [],
    "checks": [
        {
          "fails": 0,
          "name": "status is 200",
          "path": "::status is 200",
          "id": "6210a8cd14cd70477eba5c5e4cb3fb5f",
          "passes": 9002
        }
      ],
    "name": "",
    "path": ""
  },
  "options": {
    "noColor": false,
    "summaryTrendStats": [
      "avg",
      "min",
      "med",
      "max",
      "p(50)",
      "p(95)",
      "p(99)"
    ],
    "summaryTimeUnit": ""
  },
  "state": {
    "isStdOutTTY": false,
    "isStdErrTTY": false,
    "testRunDurationMs": 90016.105815
  },
  "metrics": {
    "http_req_duration{expected_response:true}": {
      "type": "trend",
      "contains": "time",
      "values": {
        "p(50)": 7.405654999999999,
        "p(95)": 9.118448599999999,
        "p(99)": 9.87063191,
        "avg": 7.376069150744272,
        "min": 2.496646,
        "med": 7.405654999999999,
        "max": 30.695951
      }
    },
    "round_trip_count": {
      "contains": "default",
      "values": {
        "p(50)": 2,
        "p(95)": 2,
        "p(99)": 2,
        "avg": 2,
        "min": 2,
        "med": 2,
        "max": 2
      },
      "type": "trend"
    },
    "http_req_tls_handshaking": {
      "type": "trend",
      "contains": "time",
      "values": {
        "min": 0,
        "med": 0,
        "max": 0,
        "p(50)": 0,
        "p(95)": 0,
        "p(99)": 0,
        "avg": 0
      }
    },
    "http_req_receiving": {
      "type": "trend",
      "contains": "time",
      "values": {
        "med": 0.084641,
        "max": 0.422945,
        "p(50)": 0.084641,
        "p(95)": 0.12891149999999998,
        "p(99)": 0.17136109999999993,
        "avg": 0.08943502766051997,
        "min": 0.040411
      }
    },
    "vus_max": {
      "type": "gauge",
      "contains": "default",
      "values": {
        "max": 100,
        "value": 100,
        "min": 100
      }
    },
    "http_req_sending": {
      "type": "trend",
      "contains": "time",
      "values": {
        "p(95)": 0.04182749999999994,
        "p(99)": 0.08353489999999987,
        "avg": 0.0233012256165297,
        "min": 0.00892,
        "med": 0.0209,
        "max": 0.487237,
        "p(50)": 0.0209
      }
    },
    "http_reqs": {
      "values": {
        "rate": 100.00432609805183,
        "count": 9002
      },
      "type": "counter",
      "contains": "default"
    },
    "http_req_duration": {
      "values": {
        "p(99)": 9.87063191,
        "avg": 7.376069150744272,
        "min": 2.496646,
        "med": 7.405654999999999,
        "max": 30.695951,
        "p(50)": 7.405654999999999,
        "p(95)": 9.118448599999999
      },
      "type": "trend",
      "contains": "time"
    },
    "payload_bytes": {
      "type": "trend",
      "contains": "default",
      "values": {
        "p(50)": 129,
        "p(95)": 2328,
        "p(99)": 2351,
        "avg": 1016.7694956676294,
        "min": 110,
        "med": 129,
        "max": 2386
      }
    },
    "data_received": {
      "type": "counter",
      "contains": "data",
      "values": {
        "count": 11506551,
        "rate": 127827.69145388406
      }
    },
    "vus": {
      "contains": "default",
      "values": {
        "min": 0,
        "max": 1,
        "value": 0
      },
      "type": "gauge"
    },
    "http_req_connecting": {
      "type": "trend",
      "contains": "time",
      "values": {
        "avg": 0.059928561986225266,
        "min": 0,
        "med": 0,
        "max": 10.031801,
        "p(50)": 0,
        "p(95)": 0,
        "p(99)": 4.103710379999977
      }
    },
    "http_req_waiting": {
      "type": "trend",
      "contains": "time",
      "values": {
        "avg": 7.263332897467235,
        "min": 2.412875,
        "med": 7.2946985,
        "max": 30.555179,
        "p(50)": 7.2946985,
        "p(95)": 9.014351,
        "p(99)": 9.755157089999999
      }
    },
    "req_latency": {
      "type": "trend",
      "contains": "default",
      "values": {
        "p(50)": 7.405654999999999,
        "p(95)": 9.118448599999999,
        "p(99)": 9.87063191,
        "avg": 7.376069150744272,
        "min": 2.496646,
        "med": 7.405654999999999,
        "max": 30.695951
      }
    },
    "checks": {
      "type": "rate",
      "contains": "default",
      "values": {
        "rate": 1,
        "passes": 9002,
        "fails": 0
      }
    },
    "iterations": {
      "type": "counter",
      "contains": "default",
      "values": {
        "count": 4501,
        "rate": 50.00216304902592
      }
    },
    "iteration_duration": {
      "type": "trend",
      "contains": "time",
      "values": {
        "med": 15.332347,
        "max": 44.726833,
        "p(50)": 15.332347,
        "p(95)": 17.942895,
        "p(99)": 21.574717,
        "avg": 15.428183893579241,
        "min": 9.68816
      }
    },
    "http_req_blocked": {
      "type": "trend",
      "contains": "time",
      "values": {
        "avg": 0.06770275005554102,
        "min": 0.00311,
        "med": 0.00611,
        "max": 10.162623,
        "p(50)": 0.00611,
        "p(95)": 0.01080949999999999,
        "p(99)": 4.196748799999977
      }
    },
    "data_sent": {
      "contains": "data",
      "values": {
        "count": 901341,
        "rate": 10013.10811925618
      },
      "type": "counter"
    },
    "page_latency": {
      "type": "trend",
      "contains": "default",
      "values": {
        "p(99)": 17.951185,
        "avg": 14.75213830148858,
        "min": 9.119002,
        "med": 14.757592,
        "max": 37.929814,
        "p(50)": 14.757592,
        "p(95)": 17.061215
      }
    },
    "http_req_failed": {
      "type": "rate",
      "contains": "default",
      "values": {
        "rate": 0,
        "passes": 0,
        "fails": 9002
      }
    }
  }
}